key_set/__init__.py
key_set/__main__.py
key_set/base.py
key_set/enum.py
key_set/py.typed
key_set-2.0.0.dist-info/METADATA
key_set-2.0.0.dist-info/WHEEL
key_set-2.0.0.dist-info/licenses/LICENSE.txt
key_set-2.0.0.dist-info/RECORD
