Metadata-Version: 2.4
Name: key_set
Version: 2.0.0
Summary: KeySet with 4 classes to represent concepts of All, None, Some, and AllExceptSome
Project-URL: Homepage, https://github.com/eturino/key_set.py
Project-URL: Repository, https://github.com/eturino/key_set.py
Author-email: Eduardo Turiño <eturino@eturino.com>
License-Expression: Apache-2.0
License-File: LICENSE.txt
Keywords: key_set,set
Classifier: Development Status :: 4 - Beta
Classifier: Intended Audience :: Developers
Classifier: License :: OSI Approved :: Apache Software License
Classifier: Natural Language :: English
Classifier: Programming Language :: Python
Classifier: Programming Language :: Python :: 3.12
Classifier: Programming Language :: Python :: 3.13
Classifier: Programming Language :: Python :: 3.14
Requires-Python: >=3.12
Provides-Extra: dev
Requires-Dist: black; extra == 'dev'
Requires-Dist: build; extra == 'dev'
Requires-Dist: bump-my-version; extra == 'dev'
Requires-Dist: mypy; extra == 'dev'
Requires-Dist: pytest; extra == 'dev'
Requires-Dist: pytest-cov; extra == 'dev'
Requires-Dist: ruff; extra == 'dev'
Requires-Dist: twine; extra == 'dev'
